MANIFEST.in
README.md
setup.cfg
setup.py
django_roesti.egg-info/PKG-INFO
django_roesti.egg-info/SOURCES.txt
django_roesti.egg-info/dependency_links.txt
django_roesti.egg-info/top_level.txt
roesti/__init__.py
roesti/models.py
roesti/tests.py