Metadata-Version: 1.1
Name: django-roesti
Version: 0.1.1
Summary: Provides a Django model keyed on the hash of its contents.
Home-page: https://github.com/danielnaab/django-roesti
Author: Daniel Naab
Author-email: dan@crushingpennies.com
License: BSD
Keywords: django
Platform: UNKNOWN
Classifier: Development Status :: 3 - Alpha
Classifier: License :: OSI Approved :: BSD License
Classifier: Intended Audience :: Developers
Classifier: Programming Language :: Python
Classifier: Programming Language :: Python :: 3
Classifier: Framework :: Django
Classifier: Framework :: Django :: 1.9
Classifier: Framework :: Django :: 1.10
